{
  "task_id": "NOAA-CLIMATE-DIAG-2024-001",
  "start_time": "2024-01-15T08:00:00+08:00",
  "end_time": "2024-01-15T09:47:23+08:00",
  "total_duration_minutes": 107,
  "phases": [
    {
      "phase": "Phase 1: Task Decomposition",
      "agents_active": [
        "Coordinator",
        "Strategist"
      ],
      "duration_min": 8,
      "api_calls": 0,
      "status": "completed"
    },
    {
      "phase": "Phase 2: Data Acquisition (GSOY)",
      "agents_active": [
        "Researcher",
        "Monitor"
      ],
      "duration_min": 35,
      "api_calls": 18,
      "details": "5 stations × 3 time periods (2000-2009, 2010-2019, 2020-2023) = 15 GSOY calls + 3 retries",
      "status": "completed"
    },
    {
      "phase": "Phase 3: GHCND Daily Sampling",
      "agents_active": [
        "Researcher",
        "Observer"
      ],
      "duration_min": 22,
      "api_calls": 10,
      "details": "5 stations × 2 periods (winter/summer 2019) for extreme events",
      "status": "completed"
    },
    {
      "phase": "Phase 4: Dimension 1-3 Analysis",
      "agents_active": [
        "Coder",
        "Analyst"
      ],
      "duration_min": 18,
      "api_calls": 0,
      "status": "completed"
    },
    {
      "phase": "Phase 5: Dimension 4-5 Analysis",
      "agents_active": [
        "Coder",
        "Analyst",
        "Strategist"
      ],
      "duration_min": 12,
      "api_calls": 0,
      "status": "completed"
    },
    {
      "phase": "Phase 6: Critic Review",
      "agents_active": [
        "Critic",
        "Analyst"
      ],
      "duration_min": 8,
      "api_calls": 0,
      "status": "completed"
    },
    {
      "phase": "Phase 7: Synthesis & Report",
      "agents_active": [
        "Synthesizer",
        "Archivist",
        "Coordinator"
      ],
      "duration_min": 4,
      "api_calls": 0,
      "status": "completed"
    }
  ],
  "api_summary": {
    "total_calls": 28,
    "GSOY_calls": 18,
    "GHCND_calls": 10,
    "failed_calls": 0,
    "retry_calls": 3,
    "rate_limit_hits": 0
  },
  "agent_interactions": 47,
  "resource_consumption": {
    "estimated_tokens": 85000,
    "data_points_retrieved": 287,
    "data_points_analyzed": 240
  },
  "warnings": [
    "济南 2013,2015-2019 GSOY数据缺失",
    "西安 2000-2005,2013,2015-2019 GSOY数据缺失",
    "极端事件统计基于2019年采样推算，非完整年度统计"
  ]
}